{
  "/markdown-page-155": {
    "__comp": "1f391b9e",
    "__context": {
      "plugin": "9f596e6d"
    },
    "content": "393be207"
  },
  "/docs-f9b": {
    "__comp": "1be78505",
    "__context": {
      "plugin": "03042d03"
    },
    "versionMetadata": "935f2afb"
  },
  "/docs/API/Boolean/is.boolean-849": {
    "__comp": "17896441",
    "content": "c710806c"
  },
  "/docs/API/Boolean/is.false-219": {
    "__comp": "17896441",
    "content": "37a6aeb6"
  },
  "/docs/API/Boolean/is.falsy-544": {
    "__comp": "17896441",
    "content": "3b1e734d"
  },
  "/docs/API/Boolean/is.true-ab9": {
    "__comp": "17896441",
    "content": "18248f9f"
  },
  "/docs/API/Boolean/is.truthy-628": {
    "__comp": "17896441",
    "content": "486b6d93"
  },
  "/docs/API/Browser/is.browser-791": {
    "__comp": "17896441",
    "content": "4a73986c"
  },
  "/docs/API/Browser/is.chrome-749": {
    "__comp": "17896441",
    "content": "c911ce8f"
  },
  "/docs/API/Browser/is.edge-ab2": {
    "__comp": "17896441",
    "content": "8b946549"
  },
  "/docs/API/Browser/is.firefox-589": {
    "__comp": "17896441",
    "content": "8ea5a03c"
  },
  "/docs/API/Browser/is.ie-ec2": {
    "__comp": "17896441",
    "content": "0cceef8f"
  },
  "/docs/API/Browser/is.opera-317": {
    "__comp": "17896441",
    "content": "1ab7636d"
  },
  "/docs/API/Browser/is.safari-df2": {
    "__comp": "17896441",
    "content": "132f3187"
  },
  "/docs/API/global-ed3": {
    "__comp": "17896441",
    "content": "f7ae576c"
  },
  "/docs/API/Hardware/is.ipad-072": {
    "__comp": "17896441",
    "content": "606db628"
  },
  "/docs/API/Hardware/is.iphone-e06": {
    "__comp": "17896441",
    "content": "8351a809"
  },
  "/docs/API/Hardware/is.ipod-fec": {
    "__comp": "17896441",
    "content": "f16f1421"
  },
  "/docs/API/Hardware/is.phone-7b4": {
    "__comp": "17896441",
    "content": "60e9d8eb"
  },
  "/docs/API/Hardware/is.windowsPhone-66e": {
    "__comp": "17896441",
    "content": "e4275023"
  },
  "/docs/API/html-b22": {
    "__comp": "17896441",
    "content": "104a1562"
  },
  "/docs/API/Number/is.bigInt-c65": {
    "__comp": "17896441",
    "content": "25d90dff"
  },
  "/docs/API/Number/is.even-d8d": {
    "__comp": "17896441",
    "content": "bf8ebd3a"
  },
  "/docs/API/Number/is.infinity-42b": {
    "__comp": "17896441",
    "content": "e97ae0e3"
  },
  "/docs/API/Number/is.int-22c": {
    "__comp": "17896441",
    "content": "b5a9f6c9"
  },
  "/docs/API/Number/is.negative-450": {
    "__comp": "17896441",
    "content": "1aceb9c2"
  },
  "/docs/API/Number/is.number-aef": {
    "__comp": "17896441",
    "content": "f207d07a"
  },
  "/docs/API/Number/is.numeric-3ec": {
    "__comp": "17896441",
    "content": "e174d26c"
  },
  "/docs/API/Number/is.odd-444": {
    "__comp": "17896441",
    "content": "e6e858d8"
  },
  "/docs/API/Number/is.positive-958": {
    "__comp": "17896441",
    "content": "8617d41a"
  },
  "/docs/API/Number/is.zero-6e6": {
    "__comp": "17896441",
    "content": "803ee3e7"
  },
  "/docs/API/rest-b4b": {
    "__comp": "17896441",
    "content": "db581bb1"
  },
  "/docs/API/String/is.camelCase-120": {
    "__comp": "17896441",
    "content": "af60db21"
  },
  "/docs/API/String/is.char-8e7": {
    "__comp": "17896441",
    "content": "27281218"
  },
  "/docs/API/String/is.ipv4-35c": {
    "__comp": "17896441",
    "content": "2e2c11c6"
  },
  "/docs/API/String/is.ipv6-086": {
    "__comp": "17896441",
    "content": "a5897b30"
  },
  "/docs/API/String/is.kebabCase-09b": {
    "__comp": "17896441",
    "content": "01d39ec5"
  },
  "/docs/API/String/is.lowerCase-1e9": {
    "__comp": "17896441",
    "content": "2b741dce"
  },
  "/docs/API/String/is.macAddress-0e6": {
    "__comp": "17896441",
    "content": "6e313f40"
  },
  "/docs/API/String/is.pascalCase-0bd": {
    "__comp": "17896441",
    "content": "bfffc999"
  },
  "/docs/API/String/is.snakeCase-1f5": {
    "__comp": "17896441",
    "content": "7865f6d9"
  },
  "/docs/API/String/is.string-b6e": {
    "__comp": "17896441",
    "content": "cd7198d4"
  },
  "/docs/API/String/is.upperCase-9f0": {
    "__comp": "17896441",
    "content": "c9bd580e"
  },
  "/docs/API/String/is.word-03a": {
    "__comp": "17896441",
    "content": "e263e339"
  },
  "/docs/API/System/is.android-7b9": {
    "__comp": "17896441",
    "content": "4e1cbdc2"
  },
  "/docs/API/System/is.ios-5e4": {
    "__comp": "17896441",
    "content": "634e4cd8"
  },
  "/docs/API/System/is.mac-21c": {
    "__comp": "17896441",
    "content": "80abfa78"
  },
  "/docs/API/System/is.windows-46f": {
    "__comp": "17896441",
    "content": "6aaf01d2"
  },
  "/docs/category/documentation---basics-e5b": {
    "__comp": "14eb3368",
    "categoryGeneratedIndex": "fe498b4e"
  },
  "/docs/category/documentation---extras-0ed": {
    "__comp": "14eb3368",
    "categoryGeneratedIndex": "58abc5c5"
  },
  "/docs/Getting started/CDN-505": {
    "__comp": "17896441",
    "content": "0bca5e0d"
  },
  "/docs/Getting started/import-74e": {
    "__comp": "17896441",
    "content": "9443bbe5"
  },
  "/docs/Getting started/install-5db": {
    "__comp": "17896441",
    "content": "18400092"
  },
  "/docs/Getting started/Introduction-462": {
    "__comp": "17896441",
    "content": "3d4d7ce3"
  },
  "/docs/tutorial-basics/congratulations-897": {
    "__comp": "17896441",
    "content": "822bd8ab"
  },
  "/docs/tutorial-basics/create-a-document-1a3": {
    "__comp": "17896441",
    "content": "1e4232ab"
  },
  "/docs/tutorial-basics/create-a-page-f4a": {
    "__comp": "17896441",
    "content": "5c868d36"
  },
  "/docs/tutorial-basics/deploy-your-site-154": {
    "__comp": "17896441",
    "content": "f55d3e7a"
  },
  "/docs/tutorial-basics/markdown-features-cd7": {
    "__comp": "17896441",
    "content": "18c41134"
  },
  "/docs/tutorial-extras/manage-docs-versions-512": {
    "__comp": "17896441",
    "content": "dff1c289"
  },
  "/docs/tutorial-extras/translate-your-site-593": {
    "__comp": "17896441",
    "content": "e44a2883"
  },
  "/-a96": {
    "__comp": "c4f5d8e4",
    "__context": {
      "plugin": "9f596e6d"
    },
    "config": "5e9f5e1a"
  }
}